{"title":"씨네21 ─ 멀티미디어 ─ 동영상","url":"http://www.cine21.com/media/video","favicon":"http://www.cine21.com/media/favicon.ico","elements":[{"title":"＜아기공룡 둘리 : 얼음별 대모험 리마스터링＞ 또치송 뮤직 클립","contents":"<!--<a href=\"/media/video/play/?qid=movie&id=44454\">-->\n\t\t\t\t\t<a href=\"/misc/jplayer/?url=http%3A%2F%2Fmp4.cine21.com%2F%2Fcine21.com%2Fmovie%2Fmaking%2F2023%2F05%2Fdully_dmmk.mp4&amp;poster=http%3A%2F%2Fk.kakaocdn.net%2Fdn%2FpizhA%2Fbtshp1vRtJa%2FkpiMZhRLgHo1ZuXjjFRCK1%2Fimg.jpg&amp;title=%EF%BC%9C%EC%95%84%EA%B8%B0%EA%B3%B5%EB%A3%A1%20%EB%91%98%EB%A6%AC%20%3A%20%EC%96%BC%EC%9D%8C%EB%B3%84%20%EB%8C%80%EB%AA%A8%ED%97%98%20%EB%A6%AC%EB%A7%88%EC%8A%A4%ED%84%B0%EB%A7%81%EF%BC%9E%20%EB%98%90%EC%B9%98%EC%86%A1%20%EB%AE%A4%EC%A7%81%20%ED%81%B4%EB%A6%BD\" data-url=\"/cine21.com/movie/making/2023/05/dully_dmmk.mp4\">\n\t\t\t\t\t\t<img src=\"http://k.kakaocdn.net/dn/pizhA/btshp1vRtJa/kpiMZhRLgHo1ZuXjjFRCK1/img.jpg\" alt=\"\" class=\"thumb\">\n\t\t\t\t\t\t<span class=\"title\">＜아기공룡 둘리 : 얼음별 대모험 리마스터링＞ 또치송 뮤직 클립</span>\n\t\t\t\t\t\t<span class=\"date\">2023-05-26</span>\n\t\t\t\t\t</a>","link":"http://www.cine21.com/misc/jplayer/?url=http%3A%2F%2Fmp4.cine21.com%2F%2Fcine21.com%2Fmovie%2Fmaking%2F2023%2F05%2Fdully_dmmk.mp4&poster=http%3A%2F%2Fk.kakaocdn.net%2Fdn%2FpizhA%2Fbtshp1vRtJa%2FkpiMZhRLgHo1ZuXjjFRCK1%2Fimg.jpg&title=%EF%BC%9C%EC%95%84%EA%B8%B0%EA%B3%B5%EB%A3%A1%20%EB%91%98%EB%A6%AC%20%3A%20%EC%96%BC%EC%9D%8C%EB%B3%84%20%EB%8C%80%EB%AA%A8%ED%97%98%20%EB%A6%AC%EB%A7%88%EC%8A%A4%ED%84%B0%EB%A7%81%EF%BC%9E%20%EB%98%90%EC%B9%98%EC%86%A1%20%EB%AE%A4%EC%A7%81%20%ED%81%B4%EB%A6%BD","retrieved":1685059200000,"image":"http://k.kakaocdn.net/dn/pizhA/btshp1vRtJa/kpiMZhRLgHo1ZuXjjFRCK1/img.jpg"},{"title":"＜귀인＞ 메인 예고편","contents":"<!--<a href=\"/media/video/play/?qid=movie&id=44453\">-->\n\t\t\t\t\t<a href=\"/misc/jplayer/?url=http%3A%2F%2Fmp4.cine21.com%2F%2Fcine21.com%2Fmovie%2Ftrailer%2F2023%2F05%2Fnobleman_mtr.mp4&amp;poster=http%3A%2F%2Fk.kakaocdn.net%2Fdn%2FcrnIwV%2Fbtshp64Q2cZ%2FKoYk9HY61KdKZuPNkBaew0%2Fimg.jpg&amp;title=%EF%BC%9C%EA%B7%80%EC%9D%B8%EF%BC%9E%20%EB%A9%94%EC%9D%B8%20%EC%98%88%EA%B3%A0%ED%8E%B8\" data-url=\"/cine21.com/movie/trailer/2023/05/nobleman_mtr.mp4\">\n\t\t\t\t\t\t<img src=\"http://k.kakaocdn.net/dn/crnIwV/btshp64Q2cZ/KoYk9HY61KdKZuPNkBaew0/img.jpg\" alt=\"\" class=\"thumb\">\n\t\t\t\t\t\t<span class=\"title\">＜귀인＞ 메인 예고편</span>\n\t\t\t\t\t\t<span class=\"date\">2023-05-26</span>\n\t\t\t\t\t</a>","link":"http://www.cine21.com/misc/jplayer/?url=http%3A%2F%2Fmp4.cine21.com%2F%2Fcine21.com%2Fmovie%2Ftrailer%2F2023%2F05%2Fnobleman_mtr.mp4&poster=http%3A%2F%2Fk.kakaocdn.net%2Fdn%2FcrnIwV%2Fbtshp64Q2cZ%2FKoYk9HY61KdKZuPNkBaew0%2Fimg.jpg&title=%EF%BC%9C%EA%B7%80%EC%9D%B8%EF%BC%9E%20%EB%A9%94%EC%9D%B8%20%EC%98%88%EA%B3%A0%ED%8E%B8","retrieved":1685059200000,"image":"http://k.kakaocdn.net/dn/crnIwV/btshp64Q2cZ/KoYk9HY61KdKZuPNkBaew0/img.jpg"},{"title":"＜1986 그 여름, 그리고 고등어통조림＞ 1차 예고편","contents":"<!--<a href=\"/media/video/play/?qid=movie&id=44452\">-->\n\t\t\t\t\t<a href=\"/misc/jplayer/?url=http%3A%2F%2Fmp4.cine21.com%2F%2Fcine21.com%2Fmovie%2Ftrailer%2F2023%2F05%2Fsabakan_1tr.mp4&amp;poster=http%3A%2F%2Fk.kakaocdn.net%2Fdn%2FbW15vG%2FbtshrSxF5tA%2FSJs0iqJgnCmMfVM3gJOqV0%2Fimg.jpg&amp;title=%EF%BC%9C1986%20%EA%B7%B8%20%EC%97%AC%EB%A6%84%2C%20%EA%B7%B8%EB%A6%AC%EA%B3%A0%20%EA%B3%A0%EB%93%B1%EC%96%B4%ED%86%B5%EC%A1%B0%EB%A6%BC%EF%BC%9E%201%EC%B0%A8%20%EC%98%88%EA%B3%A0%ED%8E%B8\" data-url=\"/cine21.com/movie/trailer/2023/05/sabakan_1tr.mp4\">\n\t\t\t\t\t\t<img src=\"http://k.kakaocdn.net/dn/bW15vG/btshrSxF5tA/SJs0iqJgnCmMfVM3gJOqV0/img.jpg\" alt=\"\" class=\"thumb\">\n\t\t\t\t\t\t<span class=\"title\">＜1986 그 여름, 그리고 고등어통조림＞ 1차 예고편</span>\n\t\t\t\t\t\t<span class=\"date\">2023-05-26</span>\n\t\t\t\t\t</a>","link":"http://www.cine21.com/misc/jplayer/?url=http%3A%2F%2Fmp4.cine21.com%2F%2Fcine21.com%2Fmovie%2Ftrailer%2F2023%2F05%2Fsabakan_1tr.mp4&poster=http%3A%2F%2Fk.kakaocdn.net%2Fdn%2FbW15vG%2FbtshrSxF5tA%2FSJs0iqJgnCmMfVM3gJOqV0%2Fimg.jpg&title=%EF%BC%9C1986%20%EA%B7%B8%20%EC%97%AC%EB%A6%84%2C%20%EA%B7%B8%EB%A6%AC%EA%B3%A0%20%EA%B3%A0%EB%93%B1%EC%96%B4%ED%86%B5%EC%A1%B0%EB%A6%BC%EF%BC%9E%201%EC%B0%A8%20%EC%98%88%EA%B3%A0%ED%8E%B8","retrieved":1685059200000,"image":"http://k.kakaocdn.net/dn/bW15vG/btshrSxF5tA/SJs0iqJgnCmMfVM3gJOqV0/img.jpg"},{"title":"＜사랑하는 당신에게＞ 제르맹’s Fantastic Life 영상","contents":"<!--<a href=\"/media/video/play/?qid=movie&id=44451\">-->\n\t\t\t\t\t<a href=\"/misc/jplayer/?url=http%3A%2F%2Fmp4.cine21.com%2F%2Fcine21.com%2Fmovie%2Fmaking%2F2023%2F05%2Flastdance_jlmk.mp4&amp;poster=http%3A%2F%2Fk.kakaocdn.net%2Fdn%2FBRKmv%2Fbtshr4SnrDE%2FpVzeK8Wxl1eXZ1aSoJipmK%2Fimg.jpg&amp;title=%EF%BC%9C%EC%82%AC%EB%9E%91%ED%95%98%EB%8A%94%20%EB%8B%B9%EC%8B%A0%EC%97%90%EA%B2%8C%EF%BC%9E%20%EC%A0%9C%EB%A5%B4%EB%A7%B9%E2%80%99s%20Fantastic%20Life%20%EC%98%81%EC%83%81\" data-url=\"/cine21.com/movie/making/2023/05/lastdance_jlmk.mp4\">\n\t\t\t\t\t\t<img src=\"http://k.kakaocdn.net/dn/BRKmv/btshr4SnrDE/pVzeK8Wxl1eXZ1aSoJipmK/img.jpg\" alt=\"\" class=\"thumb\">\n\t\t\t\t\t\t<span class=\"title\">＜사랑하는 당신에게＞ 제르맹’s Fantastic Life 영상</span>\n\t\t\t\t\t\t<span class=\"date\">2023-05-26</span>\n\t\t\t\t\t</a>","link":"http://www.cine21.com/misc/jplayer/?url=http%3A%2F%2Fmp4.cine21.com%2F%2Fcine21.com%2Fmovie%2Fmaking%2F2023%2F05%2Flastdance_jlmk.mp4&poster=http%3A%2F%2Fk.kakaocdn.net%2Fdn%2FBRKmv%2Fbtshr4SnrDE%2FpVzeK8Wxl1eXZ1aSoJipmK%2Fimg.jpg&title=%EF%BC%9C%EC%82%AC%EB%9E%91%ED%95%98%EB%8A%94%20%EB%8B%B9%EC%8B%A0%EC%97%90%EA%B2%8C%EF%BC%9E%20%EC%A0%9C%EB%A5%B4%EB%A7%B9%E2%80%99s%20Fantastic%20Life%20%EC%98%81%EC%83%81","retrieved":1685059200000,"image":"http://k.kakaocdn.net/dn/BRKmv/btshr4SnrDE/pVzeK8Wxl1eXZ1aSoJipmK/img.jpg"},{"title":"＜안나푸르나＞ 30초 예고편","contents":"<!--<a href=\"/media/video/play/?qid=movie&id=44450\">-->\n\t\t\t\t\t<a href=\"/misc/jplayer/?url=http%3A%2F%2Fmp4.cine21.com%2F%2Fcine21.com%2Fmovie%2Ftrailer%2F2023%2F05%2Fannapurna_30tr.mp4&amp;poster=http%3A%2F%2Fk.kakaocdn.net%2Fdn%2Fcy7Hvb%2Fbtshv1m52HD%2FPxXNcMPJl5RjRqqKPkem70%2Fimg.jpg&amp;title=%EF%BC%9C%EC%95%88%EB%82%98%ED%91%B8%EB%A5%B4%EB%82%98%EF%BC%9E%2030%EC%B4%88%20%EC%98%88%EA%B3%A0%ED%8E%B8\" data-url=\"/cine21.com/movie/trailer/2023/05/annapurna_30tr.mp4\">\n\t\t\t\t\t\t<img src=\"http://k.kakaocdn.net/dn/cy7Hvb/btshv1m52HD/PxXNcMPJl5RjRqqKPkem70/img.jpg\" alt=\"\" class=\"thumb\">\n\t\t\t\t\t\t<span class=\"title\">＜안나푸르나＞ 30초 예고편</span>\n\t\t\t\t\t\t<span class=\"date\">2023-05-26</span>\n\t\t\t\t\t</a>","link":"http://www.cine21.com/misc/jplayer/?url=http%3A%2F%2Fmp4.cine21.com%2F%2Fcine21.com%2Fmovie%2Ftrailer%2F2023%2F05%2Fannapurna_30tr.mp4&poster=http%3A%2F%2Fk.kakaocdn.net%2Fdn%2Fcy7Hvb%2Fbtshv1m52HD%2FPxXNcMPJl5RjRqqKPkem70%2Fimg.jpg&title=%EF%BC%9C%EC%95%88%EB%82%98%ED%91%B8%EB%A5%B4%EB%82%98%EF%BC%9E%2030%EC%B4%88%20%EC%98%88%EA%B3%A0%ED%8E%B8","retrieved":1685059200000,"image":"http://k.kakaocdn.net/dn/cy7Hvb/btshv1m52HD/PxXNcMPJl5RjRqqKPkem70/img.jpg"},{"title":"＜사슴의 왕＞ 뮤직비디오","contents":"<!--<a href=\"/media/video/play/?qid=movie&id=44449\">-->\n\t\t\t\t\t<a href=\"/misc/jplayer/?url=http%3A%2F%2Fmp4.cine21.com%2F%2Fcine21.com%2Fmovie%2Fmvideo%2F2023%2F05%2Fdeerking_mv.mp4&amp;poster=http%3A%2F%2Fk.kakaocdn.net%2Fdn%2Fbuv8Tg%2Fbtshp04J8yS%2FR1pQFBAD26eaMnmL0ColC1%2Fimg.jpg&amp;title=%EF%BC%9C%EC%82%AC%EC%8A%B4%EC%9D%98%20%EC%99%95%EF%BC%9E%20%EB%AE%A4%EC%A7%81%EB%B9%84%EB%94%94%EC%98%A4\" data-url=\"/cine21.com/movie/mvideo/2023/05/deerking_mv.mp4\">\n\t\t\t\t\t\t<img src=\"http://k.kakaocdn.net/dn/buv8Tg/btshp04J8yS/R1pQFBAD26eaMnmL0ColC1/img.jpg\" alt=\"\" class=\"thumb\">\n\t\t\t\t\t\t<span class=\"title\">＜사슴의 왕＞ 뮤직비디오</span>\n\t\t\t\t\t\t<span class=\"date\">2023-05-26</span>\n\t\t\t\t\t</a>","link":"http://www.cine21.com/misc/jplayer/?url=http%3A%2F%2Fmp4.cine21.com%2F%2Fcine21.com%2Fmovie%2Fmvideo%2F2023%2F05%2Fdeerking_mv.mp4&poster=http%3A%2F%2Fk.kakaocdn.net%2Fdn%2Fbuv8Tg%2Fbtshp04J8yS%2FR1pQFBAD26eaMnmL0ColC1%2Fimg.jpg&title=%EF%BC%9C%EC%82%AC%EC%8A%B4%EC%9D%98%20%EC%99%95%EF%BC%9E%20%EB%AE%A4%EC%A7%81%EB%B9%84%EB%94%94%EC%98%A4","retrieved":1685059200000,"image":"http://k.kakaocdn.net/dn/buv8Tg/btshp04J8yS/R1pQFBAD26eaMnmL0ColC1/img.jpg"},{"title":"＜인어공주＞ 호평 리뷰 예고편","contents":"<!--<a href=\"/media/video/play/?qid=movie&id=44448\">-->\n\t\t\t\t\t<a href=\"/misc/jplayer/?url=http%3A%2F%2Fmp4.cine21.com%2F%2Fcine21.com%2Fmovie%2Ftrailer%2F2023%2F05%2Fmermaid_rtr.mp4&amp;poster=http%3A%2F%2Fk.kakaocdn.net%2Fdn%2FdUELOW%2Fbtshp3NNeqX%2Fw0j5uk7pQSee6x9hQ4ejgk%2Fimg.jpg&amp;title=%EF%BC%9C%EC%9D%B8%EC%96%B4%EA%B3%B5%EC%A3%BC%EF%BC%9E%20%ED%98%B8%ED%8F%89%20%EB%A6%AC%EB%B7%B0%20%EC%98%88%EA%B3%A0%ED%8E%B8\" data-url=\"/cine21.com/movie/trailer/2023/05/mermaid_rtr.mp4\">\n\t\t\t\t\t\t<img src=\"http://k.kakaocdn.net/dn/dUELOW/btshp3NNeqX/w0j5uk7pQSee6x9hQ4ejgk/img.jpg\" alt=\"\" class=\"thumb\">\n\t\t\t\t\t\t<span class=\"title\">＜인어공주＞ 호평 리뷰 예고편</span>\n\t\t\t\t\t\t<span class=\"date\">2023-05-26</span>\n\t\t\t\t\t</a>","link":"http://www.cine21.com/misc/jplayer/?url=http%3A%2F%2Fmp4.cine21.com%2F%2Fcine21.com%2Fmovie%2Ftrailer%2F2023%2F05%2Fmermaid_rtr.mp4&poster=http%3A%2F%2Fk.kakaocdn.net%2Fdn%2FdUELOW%2Fbtshp3NNeqX%2Fw0j5uk7pQSee6x9hQ4ejgk%2Fimg.jpg&title=%EF%BC%9C%EC%9D%B8%EC%96%B4%EA%B3%B5%EC%A3%BC%EF%BC%9E%20%ED%98%B8%ED%8F%89%20%EB%A6%AC%EB%B7%B0%20%EC%98%88%EA%B3%A0%ED%8E%B8","retrieved":1685059200000,"image":"http://k.kakaocdn.net/dn/dUELOW/btshp3NNeqX/w0j5uk7pQSee6x9hQ4ejgk/img.jpg"},{"title":"＜육지것들＞ 예고편","contents":"<!--<a href=\"/media/video/play/?qid=movie&id=44447\">-->\n\t\t\t\t\t<a href=\"/misc/jplayer/?url=http%3A%2F%2Fmp4.cine21.com%2F%2Fcine21.com%2Fmovie%2Ftrailer%2F2023%2F05%2Fwanderers_tr.mp4&amp;poster=http%3A%2F%2Fk.kakaocdn.net%2Fdn%2Fbe99Pd%2FbtshkzxwwXY%2FIxRNZ2QoqZEDaCVa6kkeVk%2Fimg.jpg&amp;title=%EF%BC%9C%EC%9C%A1%EC%A7%80%EA%B2%83%EB%93%A4%EF%BC%9E%20%EC%98%88%EA%B3%A0%ED%8E%B8\" data-url=\"/cine21.com/movie/trailer/2023/05/wanderers_tr.mp4\">\n\t\t\t\t\t\t<img src=\"http://k.kakaocdn.net/dn/be99Pd/btshkzxwwXY/IxRNZ2QoqZEDaCVa6kkeVk/img.jpg\" alt=\"\" class=\"thumb\">\n\t\t\t\t\t\t<span class=\"title\">＜육지것들＞ 예고편</span>\n\t\t\t\t\t\t<span class=\"date\">2023-05-24</span>\n\t\t\t\t\t</a>","link":"http://www.cine21.com/misc/jplayer/?url=http%3A%2F%2Fmp4.cine21.com%2F%2Fcine21.com%2Fmovie%2Ftrailer%2F2023%2F05%2Fwanderers_tr.mp4&poster=http%3A%2F%2Fk.kakaocdn.net%2Fdn%2Fbe99Pd%2FbtshkzxwwXY%2FIxRNZ2QoqZEDaCVa6kkeVk%2Fimg.jpg&title=%EF%BC%9C%EC%9C%A1%EC%A7%80%EA%B2%83%EB%93%A4%EF%BC%9E%20%EC%98%88%EA%B3%A0%ED%8E%B8","retrieved":1684886400000,"image":"http://k.kakaocdn.net/dn/be99Pd/btshkzxwwXY/IxRNZ2QoqZEDaCVa6kkeVk/img.jpg"},{"title":"＜기적을 믿는 소녀＞ 메인 예고편","contents":"<!--<a href=\"/media/video/play/?qid=movie&id=44446\">-->\n\t\t\t\t\t<a href=\"/misc/jplayer/?url=http%3A%2F%2Fmp4.cine21.com%2F%2Fcine21.com%2Fmovie%2Ftrailer%2F2023%2F05%2Fmiracle_mtr.mp4&amp;poster=http%3A%2F%2Fk.kakaocdn.net%2Fdn%2FJaziY%2Fbtshj4qUMCQ%2FL94VdogJhjAJfAV4KkPxY0%2Fimg.jpg&amp;title=%EF%BC%9C%EA%B8%B0%EC%A0%81%EC%9D%84%20%EB%AF%BF%EB%8A%94%20%EC%86%8C%EB%85%80%EF%BC%9E%20%EB%A9%94%EC%9D%B8%20%EC%98%88%EA%B3%A0%ED%8E%B8\" data-url=\"/cine21.com/movie/trailer/2023/05/miracle_mtr.mp4\">\n\t\t\t\t\t\t<img src=\"http://k.kakaocdn.net/dn/JaziY/btshj4qUMCQ/L94VdogJhjAJfAV4KkPxY0/img.jpg\" alt=\"\" class=\"thumb\">\n\t\t\t\t\t\t<span class=\"title\">＜기적을 믿는 소녀＞ 메인 예고편</span>\n\t\t\t\t\t\t<span class=\"date\">2023-05-24</span>\n\t\t\t\t\t</a>","link":"http://www.cine21.com/misc/jplayer/?url=http%3A%2F%2Fmp4.cine21.com%2F%2Fcine21.com%2Fmovie%2Ftrailer%2F2023%2F05%2Fmiracle_mtr.mp4&poster=http%3A%2F%2Fk.kakaocdn.net%2Fdn%2FJaziY%2Fbtshj4qUMCQ%2FL94VdogJhjAJfAV4KkPxY0%2Fimg.jpg&title=%EF%BC%9C%EA%B8%B0%EC%A0%81%EC%9D%84%20%EB%AF%BF%EB%8A%94%20%EC%86%8C%EB%85%80%EF%BC%9E%20%EB%A9%94%EC%9D%B8%20%EC%98%88%EA%B3%A0%ED%8E%B8","retrieved":1684886400000,"image":"http://k.kakaocdn.net/dn/JaziY/btshj4qUMCQ/L94VdogJhjAJfAV4KkPxY0/img.jpg"},{"title":"＜북 오브 러브＞ 메인 예고편","contents":"<!--<a href=\"/media/video/play/?qid=movie&id=44445\">-->\n\t\t\t\t\t<a href=\"/misc/jplayer/?url=http%3A%2F%2Fmp4.cine21.com%2F%2Fcine21.com%2Fmovie%2Ftrailer%2F2023%2F05%2Fbooklove_mtr.mp4&amp;poster=http%3A%2F%2Fk.kakaocdn.net%2Fdn%2F5HBAp%2FbtshjdVZJZ0%2FVX6or6Us74aMxvdEkbZZMK%2Fimg.jpg&amp;title=%EF%BC%9C%EB%B6%81%20%EC%98%A4%EB%B8%8C%20%EB%9F%AC%EB%B8%8C%EF%BC%9E%20%EB%A9%94%EC%9D%B8%20%EC%98%88%EA%B3%A0%ED%8E%B8\" data-url=\"/cine21.com/movie/trailer/2023/05/booklove_mtr.mp4\">\n\t\t\t\t\t\t<img src=\"http://k.kakaocdn.net/dn/5HBAp/btshjdVZJZ0/VX6or6Us74aMxvdEkbZZMK/img.jpg\" alt=\"\" class=\"thumb\">\n\t\t\t\t\t\t<span class=\"title\">＜북 오브 러브＞ 메인 예고편</span>\n\t\t\t\t\t\t<span class=\"date\">2023-05-24</span>\n\t\t\t\t\t</a>","link":"http://www.cine21.com/misc/jplayer/?url=http%3A%2F%2Fmp4.cine21.com%2F%2Fcine21.com%2Fmovie%2Ftrailer%2F2023%2F05%2Fbooklove_mtr.mp4&poster=http%3A%2F%2Fk.kakaocdn.net%2Fdn%2F5HBAp%2FbtshjdVZJZ0%2FVX6or6Us74aMxvdEkbZZMK%2Fimg.jpg&title=%EF%BC%9C%EB%B6%81%20%EC%98%A4%EB%B8%8C%20%EB%9F%AC%EB%B8%8C%EF%BC%9E%20%EB%A9%94%EC%9D%B8%20%EC%98%88%EA%B3%A0%ED%8E%B8","retrieved":1684886400000,"image":"http://k.kakaocdn.net/dn/5HBAp/btshjdVZJZ0/VX6or6Us74aMxvdEkbZZMK/img.jpg"},{"title":"＜너의 눈을 들여다보면＞ 메인 예고편","contents":"<!--<a href=\"/media/video/play/?qid=movie&id=44443\">-->\n\t\t\t\t\t<a href=\"/misc/jplayer/?url=http%3A%2F%2Fmp4.cine21.com%2F%2Fcine21.com%2Fmovie%2Ftrailer%2F2023%2F05%2Fsteady_mtr.mp4&amp;poster=http%3A%2F%2Fk.kakaocdn.net%2Fdn%2FqbjT7%2FbtshaTLqjP8%2FSH8WykxxOm3A5wlzKfwHmK%2Fimg.jpg&amp;title=%EF%BC%9C%EB%84%88%EC%9D%98%20%EB%88%88%EC%9D%84%20%EB%93%A4%EC%97%AC%EB%8B%A4%EB%B3%B4%EB%A9%B4%EF%BC%9E%20%EB%A9%94%EC%9D%B8%20%EC%98%88%EA%B3%A0%ED%8E%B8\" data-url=\"/cine21.com/movie/trailer/2023/05/steady_mtr.mp4\">\n\t\t\t\t\t\t<img src=\"http://k.kakaocdn.net/dn/qbjT7/btshaTLqjP8/SH8WykxxOm3A5wlzKfwHmK/img.jpg\" alt=\"\" class=\"thumb\">\n\t\t\t\t\t\t<span class=\"title\">＜너의 눈을 들여다보면＞ 메인 예고편</span>\n\t\t\t\t\t\t<span class=\"date\">2023-05-24</span>\n\t\t\t\t\t</a>","link":"http://www.cine21.com/misc/jplayer/?url=http%3A%2F%2Fmp4.cine21.com%2F%2Fcine21.com%2Fmovie%2Ftrailer%2F2023%2F05%2Fsteady_mtr.mp4&poster=http%3A%2F%2Fk.kakaocdn.net%2Fdn%2FqbjT7%2FbtshaTLqjP8%2FSH8WykxxOm3A5wlzKfwHmK%2Fimg.jpg&title=%EF%BC%9C%EB%84%88%EC%9D%98%20%EB%88%88%EC%9D%84%20%EB%93%A4%EC%97%AC%EB%8B%A4%EB%B3%B4%EB%A9%B4%EF%BC%9E%20%EB%A9%94%EC%9D%B8%20%EC%98%88%EA%B3%A0%ED%8E%B8","retrieved":1684886400000,"image":"http://k.kakaocdn.net/dn/qbjT7/btshaTLqjP8/SH8WykxxOm3A5wlzKfwHmK/img.jpg"},{"title":"＜하나님의 마음＞ 메인 예고편","contents":"<!--<a href=\"/media/video/play/?qid=movie&id=44442\">-->\n\t\t\t\t\t<a href=\"/misc/jplayer/?url=http%3A%2F%2Fmp4.cine21.com%2F%2Fcine21.com%2Fmovie%2Ftrailer%2F2023%2F05%2Fhisson_mtr.mp4&amp;poster=http%3A%2F%2Fk.kakaocdn.net%2Fdn%2F3sxjv%2Fbtsg9MrExCT%2FoD3uFs6YnWeJfMwDLqfCTk%2Fimg.jpg&amp;title=%EF%BC%9C%ED%95%98%EB%82%98%EB%8B%98%EC%9D%98%20%EB%A7%88%EC%9D%8C%EF%BC%9E%20%EB%A9%94%EC%9D%B8%20%EC%98%88%EA%B3%A0%ED%8E%B8\" data-url=\"/cine21.com/movie/trailer/2023/05/hisson_mtr.mp4\">\n\t\t\t\t\t\t<img src=\"http://k.kakaocdn.net/dn/3sxjv/btsg9MrExCT/oD3uFs6YnWeJfMwDLqfCTk/img.jpg\" alt=\"\" class=\"thumb\">\n\t\t\t\t\t\t<span class=\"title\">＜하나님의 마음＞ 메인 예고편</span>\n\t\t\t\t\t\t<span class=\"date\">2023-05-24</span>\n\t\t\t\t\t</a>","link":"http://www.cine21.com/misc/jplayer/?url=http%3A%2F%2Fmp4.cine21.com%2F%2Fcine21.com%2Fmovie%2Ftrailer%2F2023%2F05%2Fhisson_mtr.mp4&poster=http%3A%2F%2Fk.kakaocdn.net%2Fdn%2F3sxjv%2Fbtsg9MrExCT%2FoD3uFs6YnWeJfMwDLqfCTk%2Fimg.jpg&title=%EF%BC%9C%ED%95%98%EB%82%98%EB%8B%98%EC%9D%98%20%EB%A7%88%EC%9D%8C%EF%BC%9E%20%EB%A9%94%EC%9D%B8%20%EC%98%88%EA%B3%A0%ED%8E%B8","retrieved":1684886400000,"image":"http://k.kakaocdn.net/dn/3sxjv/btsg9MrExCT/oD3uFs6YnWeJfMwDLqfCTk/img.jpg"},{"title":"＜빅트립2: 아기곰 배달 대작전＞ 스페셜 대륙 횡단 영상","contents":"<!--<a href=\"/media/video/play/?qid=movie&id=44441\">-->\n\t\t\t\t\t<a href=\"/misc/jplayer/?url=http%3A%2F%2Fmp4.cine21.com%2F%2Fcine21.com%2Fmovie%2Fmaking%2F2023%2F05%2Fbigtrip2_sdmk.mp4&amp;poster=http%3A%2F%2Fk.kakaocdn.net%2Fdn%2FcCdnRh%2Fbtshbenz3RW%2F2hTevKHbhKuXqN8HGWJQN0%2Fimg.jpg&amp;title=%EF%BC%9C%EB%B9%85%ED%8A%B8%EB%A6%BD2%3A%20%EC%95%84%EA%B8%B0%EA%B3%B0%20%EB%B0%B0%EB%8B%AC%20%EB%8C%80%EC%9E%91%EC%A0%84%EF%BC%9E%20%EC%8A%A4%ED%8E%98%EC%85%9C%20%EB%8C%80%EB%A5%99%20%ED%9A%A1%EB%8B%A8%20%EC%98%81%EC%83%81\" data-url=\"/cine21.com/movie/making/2023/05/bigtrip2_sdmk.mp4\">\n\t\t\t\t\t\t<img src=\"http://k.kakaocdn.net/dn/cCdnRh/btshbenz3RW/2hTevKHbhKuXqN8HGWJQN0/img.jpg\" alt=\"\" class=\"thumb\">\n\t\t\t\t\t\t<span class=\"title\">＜빅트립2: 아기곰 배달 대작전＞ 스페셜 대륙 횡단 영상</span>\n\t\t\t\t\t\t<span class=\"date\">2023-05-24</span>\n\t\t\t\t\t</a>","link":"http://www.cine21.com/misc/jplayer/?url=http%3A%2F%2Fmp4.cine21.com%2F%2Fcine21.com%2Fmovie%2Fmaking%2F2023%2F05%2Fbigtrip2_sdmk.mp4&poster=http%3A%2F%2Fk.kakaocdn.net%2Fdn%2FcCdnRh%2Fbtshbenz3RW%2F2hTevKHbhKuXqN8HGWJQN0%2Fimg.jpg&title=%EF%BC%9C%EB%B9%85%ED%8A%B8%EB%A6%BD2%3A%20%EC%95%84%EA%B8%B0%EA%B3%B0%20%EB%B0%B0%EB%8B%AC%20%EB%8C%80%EC%9E%91%EC%A0%84%EF%BC%9E%20%EC%8A%A4%ED%8E%98%EC%85%9C%20%EB%8C%80%EB%A5%99%20%ED%9A%A1%EB%8B%A8%20%EC%98%81%EC%83%81","retrieved":1684886400000,"image":"http://k.kakaocdn.net/dn/cCdnRh/btshbenz3RW/2hTevKHbhKuXqN8HGWJQN0/img.jpg"},{"title":"＜마인드케이지＞ 메인 예고편","contents":"<!--<a href=\"/media/video/play/?qid=movie&id=44440\">-->\n\t\t\t\t\t<a href=\"/misc/jplayer/?url=http%3A%2F%2Fmp4.cine21.com%2F%2Fcine21.com%2Fmovie%2Ftrailer%2F2023%2F05%2Fmindcage_mtr.mp4&amp;poster=http%3A%2F%2Fk.kakaocdn.net%2Fdn%2Fbwjp4K%2Fbtshb7IskP4%2FiktY0W4kHN1e6QdHBLvFf1%2Fimg.jpg&amp;title=%EF%BC%9C%EB%A7%88%EC%9D%B8%EB%93%9C%EC%BC%80%EC%9D%B4%EC%A7%80%EF%BC%9E%20%EB%A9%94%EC%9D%B8%20%EC%98%88%EA%B3%A0%ED%8E%B8\" data-url=\"/cine21.com/movie/trailer/2023/05/mindcage_mtr.mp4\">\n\t\t\t\t\t\t<img src=\"http://k.kakaocdn.net/dn/bwjp4K/btshb7IskP4/iktY0W4kHN1e6QdHBLvFf1/img.jpg\" alt=\"\" class=\"thumb\">\n\t\t\t\t\t\t<span class=\"title\">＜마인드케이지＞ 메인 예고편</span>\n\t\t\t\t\t\t<span class=\"date\">2023-05-24</span>\n\t\t\t\t\t</a>","link":"http://www.cine21.com/misc/jplayer/?url=http%3A%2F%2Fmp4.cine21.com%2F%2Fcine21.com%2Fmovie%2Ftrailer%2F2023%2F05%2Fmindcage_mtr.mp4&poster=http%3A%2F%2Fk.kakaocdn.net%2Fdn%2Fbwjp4K%2Fbtshb7IskP4%2FiktY0W4kHN1e6QdHBLvFf1%2Fimg.jpg&title=%EF%BC%9C%EB%A7%88%EC%9D%B8%EB%93%9C%EC%BC%80%EC%9D%B4%EC%A7%80%EF%BC%9E%20%EB%A9%94%EC%9D%B8%20%EC%98%88%EA%B3%A0%ED%8E%B8","retrieved":1684886400000,"image":"http://k.kakaocdn.net/dn/bwjp4K/btshb7IskP4/iktY0W4kHN1e6QdHBLvFf1/img.jpg"},{"title":"＜인어공주＞ ‘Part of Your World’ 영상","contents":"<!--<a href=\"/media/video/play/?qid=movie&id=44439\">-->\n\t\t\t\t\t<a href=\"/misc/jplayer/?url=http%3A%2F%2Fmp4.cine21.com%2F%2Fcine21.com%2Fmovie%2Fmaking%2F2023%2F05%2Fmermaid_pwmk.mp4&amp;poster=http%3A%2F%2Fk.kakaocdn.net%2Fdn%2FJH9Ym%2Fbtsg4heWeq2%2FafIsAb2bSTFQ5kEkdkNVz0%2Fimg.jpg&amp;title=%EF%BC%9C%EC%9D%B8%EC%96%B4%EA%B3%B5%EC%A3%BC%EF%BC%9E%20%E2%80%98Part%20of%20Your%20World%E2%80%99%20%EC%98%81%EC%83%81\" data-url=\"/cine21.com/movie/making/2023/05/mermaid_pwmk.mp4\">\n\t\t\t\t\t\t<img src=\"http://k.kakaocdn.net/dn/JH9Ym/btsg4heWeq2/afIsAb2bSTFQ5kEkdkNVz0/img.jpg\" alt=\"\" class=\"thumb\">\n\t\t\t\t\t\t<span class=\"title\">＜인어공주＞ ‘Part of Your World’ 영상</span>\n\t\t\t\t\t\t<span class=\"date\">2023-05-24</span>\n\t\t\t\t\t</a>","link":"http://www.cine21.com/misc/jplayer/?url=http%3A%2F%2Fmp4.cine21.com%2F%2Fcine21.com%2Fmovie%2Fmaking%2F2023%2F05%2Fmermaid_pwmk.mp4&poster=http%3A%2F%2Fk.kakaocdn.net%2Fdn%2FJH9Ym%2Fbtsg4heWeq2%2FafIsAb2bSTFQ5kEkdkNVz0%2Fimg.jpg&title=%EF%BC%9C%EC%9D%B8%EC%96%B4%EA%B3%B5%EC%A3%BC%EF%BC%9E%20%E2%80%98Part%20of%20Your%20World%E2%80%99%20%EC%98%81%EC%83%81","retrieved":1684886400000,"image":"http://k.kakaocdn.net/dn/JH9Ym/btsg4heWeq2/afIsAb2bSTFQ5kEkdkNVz0/img.jpg"},{"title":"＜인어공주＞ ‘꿈꾸던 세상’ 예고편","contents":"<!--<a href=\"/media/video/play/?qid=movie&id=44438\">-->\n\t\t\t\t\t<a href=\"/misc/jplayer/?url=http%3A%2F%2Fmp4.cine21.com%2F%2Fcine21.com%2Fmovie%2Ftrailer%2F2023%2F05%2Fmermaid_dwtr.mp4&amp;poster=http%3A%2F%2Fk.kakaocdn.net%2Fdn%2F1iR58%2FbtshbsF04WB%2FWjVN1ZfMZZiFHEwfjgCLY0%2Fimg.jpg&amp;title=%EF%BC%9C%EC%9D%B8%EC%96%B4%EA%B3%B5%EC%A3%BC%EF%BC%9E%20%E2%80%98%EA%BF%88%EA%BE%B8%EB%8D%98%20%EC%84%B8%EC%83%81%E2%80%99%20%EC%98%88%EA%B3%A0%ED%8E%B8\" data-url=\"/cine21.com/movie/trailer/2023/05/mermaid_dwtr.mp4\">\n\t\t\t\t\t\t<img src=\"http://k.kakaocdn.net/dn/1iR58/btshbsF04WB/WjVN1ZfMZZiFHEwfjgCLY0/img.jpg\" alt=\"\" class=\"thumb\">\n\t\t\t\t\t\t<span class=\"title\">＜인어공주＞ ‘꿈꾸던 세상’ 예고편</span>\n\t\t\t\t\t\t<span class=\"date\">2023-05-24</span>\n\t\t\t\t\t</a>","link":"http://www.cine21.com/misc/jplayer/?url=http%3A%2F%2Fmp4.cine21.com%2F%2Fcine21.com%2Fmovie%2Ftrailer%2F2023%2F05%2Fmermaid_dwtr.mp4&poster=http%3A%2F%2Fk.kakaocdn.net%2Fdn%2F1iR58%2FbtshbsF04WB%2FWjVN1ZfMZZiFHEwfjgCLY0%2Fimg.jpg&title=%EF%BC%9C%EC%9D%B8%EC%96%B4%EA%B3%B5%EC%A3%BC%EF%BC%9E%20%E2%80%98%EA%BF%88%EA%BE%B8%EB%8D%98%20%EC%84%B8%EC%83%81%E2%80%99%20%EC%98%88%EA%B3%A0%ED%8E%B8","retrieved":1684886400000,"image":"http://k.kakaocdn.net/dn/1iR58/btshbsF04WB/WjVN1ZfMZZiFHEwfjgCLY0/img.jpg"}]}