{"title":"씨네21 ─ 시사회&이벤트 ─ 진행중인 이벤트","url":"http://www.cine21.com/event/list","favicon":"http://www.cine21.com/event/favicon.ico","elements":[{"title":"뮤지컬 <망원동 브라더스> 초대 이벤트","contents":"<p><span class=\"tit\">인원</span><span class=\"bar\">|</span>10 명</p>\n                        <p><span class=\"tit\">발표</span><span class=\"bar\">|</span>2024-04-15 18:00</p>","link":"http://www.cine21.com/event/view/?event_no=8301","retrieved":1712114499822,"image":"https://image.cine21.com/resize/cine21/movie/2024/0403/11_46_38__660cc30ee67c3[T224,320].png"},{"title":"도서 <불꽃> 기대평 이벤트","contents":"<p><span class=\"tit\">인원</span><span class=\"bar\">|</span>10 명</p>\n                        <p><span class=\"tit\">발표</span><span class=\"bar\">|</span>2024-04-11 18:00</p>","link":"http://www.cine21.com/event/view/?event_no=8300","retrieved":1712114499824,"image":"https://image.cine21.com/resize/cine21/movie/2024/0403/11_42_57__660cc23152399[T224,320].png"},{"title":"도서 <무기모토 산포는 내일이 좋아> 기대평 이벤트","contents":"<p><span class=\"tit\">인원</span><span class=\"bar\">|</span>10 명</p>\n                        <p><span class=\"tit\">발표</span><span class=\"bar\">|</span>2024-04-11 18:00</p>","link":"http://www.cine21.com/event/view/?event_no=8299","retrieved":1712114499825,"image":"https://image.cine21.com/resize/cine21/movie/2024/0403/11_41_29__660cc1d97d008[T224,320].jpg"},{"title":"연극 <늘근도둑 이야기> 초대 이벤트","contents":"<p><span class=\"tit\">인원</span><span class=\"bar\">|</span>30 명</p>\n                        <p><span class=\"tit\">발표</span><span class=\"bar\">|</span>2024-04-11 18:00</p>","link":"http://www.cine21.com/event/view/?event_no=8298","retrieved":1711984634288,"image":"https://image.cine21.com/resize/cine21/movie/2024/0402/00_06_43__660acd8342ca1[T224,320].jpg"},{"title":"연극 <오백에 삼십> 초대 이벤트","contents":"<p><span class=\"tit\">인원</span><span class=\"bar\">|</span>15 명</p>\n                        <p><span class=\"tit\">발표</span><span class=\"bar\">|</span>2024-04-08 15:00</p>","link":"http://www.cine21.com/event/view/?event_no=8297","retrieved":1711523911002,"image":"https://image.cine21.com/resize/cine21/movie/2024/0327/16_13_34__6603c71e775e3[T224,320].jpg"},{"title":"뮤지컬 <파가니니> 초대 이벤트","contents":"<p><span class=\"tit\">인원</span><span class=\"bar\">|</span>10 명</p>\n                        <p><span class=\"tit\">발표</span><span class=\"bar\">|</span>2024-04-08 18:00</p>","link":"http://www.cine21.com/event/view/?event_no=8291","retrieved":1710688852397,"image":"https://image.cine21.com/resize/cine21/event/2024/0315/18_58_49__65f41bd9bfdca[T224,320].jpg"}]}