{"title":"씨네21 ─ 영화 ─ 개봉일 확정","url":"http://www.cine21.com/movie/lists/coming_date","favicon":"http://www.cine21.com/movie/lists/favicon.ico","elements":[{"title":"아라시 20주년 투어 콘서트 5X20","contents":"개봉 : 2022-08-31","link":"http://www.cine21.com/movie/info/?movie_id=59496","retrieved":1661264448108,"image":"https://image.cine21.com/resize/cine21/poster/2022/0810/16_20_20__62f35c3409178[X224,320].jpg"},{"title":"시맨틱 에러: 더 무비","contents":"개봉 : 2022-08-31","link":"http://www.cine21.com/movie/info/?movie_id=59433","retrieved":1661160104881,"image":"https://image.cine21.com/resize/cine21/poster/2022/0728/12_14_02__62e1fefa0db0c[X224,320].jpg"},{"title":"썬다운","contents":"개봉 : 2022-08-31","link":"http://www.cine21.com/movie/info/?movie_id=59473","retrieved":1661282307817,"image":"https://image.cine21.com/resize/cine21/poster/2022/0811/17_39_36__62f4c048ef247[X224,320].jpg"},{"title":"리미트","contents":"개봉 : 2022-08-31","link":"http://www.cine21.com/movie/info/?movie_id=59345","retrieved":1661282307807,"image":"https://image.cine21.com/resize/cine21/poster/2022/0803/18_15_28__62ea3cb0acafa[X224,320].jpg"},{"title":"락다운 213주","contents":"개봉 : 2022-08-31","link":"http://www.cine21.com/movie/info/?movie_id=59403","retrieved":1661282307806,"image":"https://image.cine21.com/resize/cine21/poster/2022/0805/15_15_51__62ecb597ba98b[X224,320].jpg"},{"title":"K클래식 제너레이션","contents":"개봉 : 2022-08-31","link":"http://www.cine21.com/movie/info/?movie_id=59506","retrieved":1661282307817,"image":"https://image.cine21.com/resize/cine21/poster/2022/0823/15_04_47__63046dff98120[X224,320].jpg"},{"title":"우리가 말하지 않은 것","contents":"개봉 : 2022-09-01","link":"http://www.cine21.com/movie/info/?movie_id=59421","retrieved":1661358476833,"image":"https://image.cine21.com/resize/cine21/poster/2022/0808/13_47_53__62f095790b04e[X224,320].jpg"},{"title":"데인저 파크","contents":"개봉 : 2022-09-01","link":"http://www.cine21.com/movie/info/?movie_id=59568","retrieved":1661322582212,"image":"https://image.cine21.com/resize/cine21/poster/2022/0825/16_08_44__63071ffc4cb39[X224,320].jpg"},{"title":"쥬라기캅스 극장판: 공룡시대 대모험","contents":"개봉 : 2022-09-07","link":"http://www.cine21.com/movie/info/?movie_id=59498","retrieved":1661358476874,"image":"https://image.cine21.com/resize/cine21/poster/2022/0824/14_19_40__6305b4ec74a92[X224,320].jpg"},{"title":"인생은 뷰티풀: 비타돌체","contents":"개봉 : 2022-09-07","link":"http://www.cine21.com/movie/info/?movie_id=59576","retrieved":1661435166056,"image":"https://image.cine21.com/resize/cine21/poster/2022/0826/11_09_51__63082b6f4a76d[X224,320].jpg"},{"title":"블레이즈","contents":"개봉 : 2022-09-07","link":"http://www.cine21.com/movie/info/?movie_id=59347","retrieved":1661358476834,"image":"https://image.cine21.com/resize/cine21/poster/2022/0824/15_30_26__6305c582e7758[X224,320].jpg"},{"title":"공조2: 인터내셔날","contents":"개봉 : 2022-09-07","link":"http://www.cine21.com/movie/info/?movie_id=57553","retrieved":1661358476873,"image":"https://image.cine21.com/resize/cine21/poster/2022/0826/12_30_09__63083e410eb65[X224,320].jpg"},{"title":"블랙폰","contents":"개봉 : 2022-09-07","link":"http://www.cine21.com/movie/info/?movie_id=58784","retrieved":1661358476838,"image":"https://image.cine21.com/resize/cine21/poster/2022/0804/10_08_01__62eb1bf1a374f[X224,320].jpg"},{"title":"다 잘된 거야","contents":"개봉 : 2022-09-07","link":"http://www.cine21.com/movie/info/?movie_id=58598","retrieved":1661358476844,"image":"https://image.cine21.com/resize/cine21/poster/2022/0818/11_46_20__62fda7fca251f[X224,320].jpg"},{"title":"부적: 남의 운을 빼앗는 자","contents":"개봉 : 2022-09-07","link":"http://www.cine21.com/movie/info/?movie_id=59560","retrieved":1661358476849,"image":"https://image.cine21.com/resize/cine21/poster/2022/0818/18_10_04__62fe01ecbb100[X224,320].jpg"},{"title":"모가디슈","contents":"개봉 : 2022-09-07","link":"http://www.cine21.com/movie/info/?movie_id=57275","retrieved":1661358476848,"image":"https://image.cine21.com/resize/cine21/poster/2021/0825/57275_6125e1f110d88[X224,320].jpg"},{"title":"극장판 엄마 까투리: 도시로 간 까투리 가족","contents":"개봉 : 2022-09-08","link":"http://www.cine21.com/movie/info/?movie_id=59434","retrieved":1661790300187,"image":"https://image.cine21.com/resize/cine21/poster/2022/0823/16_19_06__63047f6aca279[X224,320].jpg"},{"title":"노후자금이 없어!","contents":"개봉 : 2022-09-08","link":"http://www.cine21.com/movie/info/?movie_id=59579","retrieved":1661517399324,"image":"https://image.cine21.com/resize/cine21/poster/2022/0826/18_31_25__630892ed662fa[X224,320].jpg"}]}