{"title":"씨네21 ─ 영화 ─ 개봉일 확정","url":"http://www.cine21.com/movie/lists/coming_date","favicon":"http://www.cine21.com/movie/lists/favicon.ico","elements":[{"title":"파일럿: 배틀 포 서바이벌","contents":"개봉 : 2022-04-13","link":"http://www.cine21.com/movie/info/?movie_id=58685","retrieved":1648574397631,"image":"https://image.cine21.com/resize/cine21/poster/2022/0316/13_02_14__623161460e8bc[X224,320].jpg"},{"title":"행복을 전하는 편지","contents":"개봉 : 2022-04-13","link":"http://www.cine21.com/movie/info/?movie_id=59038","retrieved":1648700471858,"image":"https://image.cine21.com/resize/cine21/poster/2022/0331/59038_6245261e1c6f8[X224,320].jpg"},{"title":"신비한 동물들과 덤블도어의 비밀","contents":"개봉 : 2022-04-13","link":"http://www.cine21.com/movie/info/?movie_id=59003","retrieved":1648574397630,"image":"https://image.cine21.com/resize/cine21/poster/2022/0325/11_36_47__623d2abf1e647[X224,320].jpg"},{"title":"말임씨를 부탁해","contents":"개봉 : 2022-04-13","link":"http://www.cine21.com/movie/info/?movie_id=59017","retrieved":1648574397628,"image":"https://image.cine21.com/resize/cine21/poster/2022/0401/59017_6246585584824[X224,320].jpg"},{"title":"고스팅 글로리아","contents":"개봉 : 2022-04-14","link":"http://www.cine21.com/movie/info/?movie_id=59025","retrieved":1648660638672,"image":"https://image.cine21.com/resize/cine21/poster/2022/0330/09_41_12__6243a728c94ee[X224,320].jpg"},{"title":"3.5교시","contents":"개봉 : 2022-04-14","link":"http://www.cine21.com/movie/info/?movie_id=59047","retrieved":1648178445150,"image":"https://image.cine21.com/resize/cine21/poster/2022/0330/59047_6243abcc0bc6f[X224,320].jpg"},{"title":"엄마와 나","contents":"개봉 : 2022-04-14","link":"http://www.cine21.com/movie/info/?movie_id=59051","retrieved":1649135800459,"image":"https://image.cine21.com/resize/cine21/poster/2022/0323/59051_623a893b05718[X224,320].jpg"},{"title":"웨이트: 감각에 눈뜰 때","contents":"개봉 : 2022-04-14","link":"http://www.cine21.com/movie/info/?movie_id=59063","retrieved":1649135800456,"image":"https://image.cine21.com/resize/cine21/poster/2022/0330/59063_6243af01c6b0d[X224,320].jpg"},{"title":"복지식당","contents":"개봉 : 2022-04-14","link":"http://www.cine21.com/movie/info/?movie_id=57981","retrieved":1649186067718,"image":"https://image.cine21.com/resize/cine21/poster/2022/0321/57981_6237dbd274cac[X224,320].jpg"},{"title":"그리스도 디 오리진","contents":"개봉 : 2022-04-14","link":"http://www.cine21.com/movie/info/?movie_id=59027","retrieved":1648574397634,"image":"https://image.cine21.com/resize/cine21/poster/2022/0331/59027_62452344ddefc[X224,320].jpg"},{"title":"너도 평범하지 않아","contents":"개봉 : 2022-04-14","link":"http://www.cine21.com/movie/info/?movie_id=59073","retrieved":1649272408785,"image":"https://image.cine21.com/resize/cine21/poster/2022/0406/59073_624d10a4b7fcd[X224,320].jpg"},{"title":"태어나길 잘했어","contents":"개봉 : 2022-04-14","link":"http://www.cine21.com/movie/info/?movie_id=57689","retrieved":1648602154457,"image":"https://image.cine21.com/resize/cine21/poster/2022/0329/57689_6242916ed367d[X224,320].jpg"},{"title":"세븐틴 파워 오브 러브 : 더 무비","contents":"개봉 : 2022-04-20","link":"http://www.cine21.com/movie/info/?movie_id=59029","retrieved":1649186067732,"image":"https://image.cine21.com/resize/cine21/poster/2022/0310/59029_622964ad9e9ab[X224,320].jpg"},{"title":"앵커","contents":"개봉 : 2022-04-20","link":"http://www.cine21.com/movie/info/?movie_id=55496","retrieved":1649272408798,"image":"https://image.cine21.com/resize/cine21/poster/2022/0331/55496_624528e66f09f[X224,320].jpg"},{"title":"4월은 너의 거짓말","contents":"개봉 : 2022-04-20","link":"http://www.cine21.com/movie/info/?movie_id=48899","retrieved":1649186067733,"image":"https://image.cine21.com/resize/cine21/poster/2022/0404/10_59_52__624a5118ea795[X224,320].jpg"},{"title":"로스트 시티","contents":"개봉 : 2022-04-20","link":"http://www.cine21.com/movie/info/?movie_id=58793","retrieved":1649186067718,"image":"https://image.cine21.com/resize/cine21/poster/2022/0321/58793_6237e163282e8[X224,320].jpg"},{"title":"쓰리: 아직 끝나지 않았다","contents":"개봉 : 2022-04-21","link":"http://www.cine21.com/movie/info/?movie_id=57080","retrieved":1649737219241,"image":"https://image.cine21.com/resize/cine21/poster/2022/0321/57080_6237d96346f37[X224,320].jpg"},{"title":"위대한 계약: 파주, 책, 도시","contents":"개봉 : 2022-04-21","link":"http://www.cine21.com/movie/info/?movie_id=57696","retrieved":1649737219246,"image":"https://image.cine21.com/resize/cine21/poster/2022/0329/14_52_32__62429ea099eee[X224,320].jpg"}]}