{"title":"씨네21 ─ 영화 ─ 개봉일 확정","url":"http://www.cine21.com/movie/lists/coming_date","favicon":"http://www.cine21.com/movie/lists/favicon.ico","elements":[{"title":"크레센도 반 클라이번 콩쿠르 실황","contents":"개봉 : 2024-01-31","link":"http://www.cine21.com/movie/info/?movie_id=61218","retrieved":1706512637964,"image":"https://image.cine21.com/resize/cine21/poster/2024/0129/16_19_58__65b7519e87129[X224,320].jpg"},{"title":"킹덤: 엑소더스","contents":"개봉 : 2024-01-31","link":"http://www.cine21.com/movie/info/?movie_id=61169","retrieved":1705559003984,"image":"https://image.cine21.com/resize/cine21/poster/2024/0118/16_01_27__65a8ccc7aec5a[X224,320].jpg"},{"title":"아녜스 V에 의한 제인 B","contents":"개봉 : 2024-01-31","link":"http://www.cine21.com/movie/info/?movie_id=61160","retrieved":1705629692818,"image":"https://image.cine21.com/resize/cine21/poster/2024/0117/10_45_22__65a73132383b8[X224,320].jpg"},{"title":"정글번치 : 월드투어","contents":"개봉 : 2024-01-31","link":"http://www.cine21.com/movie/info/?movie_id=61128","retrieved":1705998167695,"image":"https://image.cine21.com/resize/cine21/poster/2024/0116/16_42_05__65a6334deb43a[X224,320].jpg"},{"title":"아톰 새로운 시작","contents":"개봉 : 2024-01-31","link":"http://www.cine21.com/movie/info/?movie_id=61122","retrieved":1705885303410,"image":"https://image.cine21.com/resize/cine21/poster/2024/0123/17_34_39__65af7a1f84160[X224,320].jpg"},{"title":"추락의 해부","contents":"개봉 : 2024-01-31","link":"http://www.cine21.com/movie/info/?movie_id=61106","retrieved":1705998167698,"image":"https://image.cine21.com/resize/cine21/poster/2024/0117/13_44_10__65a75b1adf3df[X224,320].jpg"},{"title":"두 세계 사이에서","contents":"개봉 : 2024-01-31","link":"http://www.cine21.com/movie/info/?movie_id=61102","retrieved":1706026966048,"image":"https://image.cine21.com/resize/cine21/poster/2024/0118/16_13_17__65a8cf8d73b11[X224,320].jpg"},{"title":"웡카","contents":"개봉 : 2024-01-31","link":"http://www.cine21.com/movie/info/?movie_id=61087","retrieved":1706026966064,"image":"https://image.cine21.com/resize/cine21/poster/2024/0105/16_40_56__6597b2885dbe0[X224,320].jpg"},{"title":"비욘드 유토피아","contents":"개봉 : 2024-01-31","link":"http://www.cine21.com/movie/info/?movie_id=60479","retrieved":1706026966057,"image":"https://image.cine21.com/resize/cine21/poster/2024/0109/15_25_22__659ce6d27d667[X224,320].jpg"},{"title":"부활 그 소망","contents":"개봉 : 2024-02-00","link":"http://www.cine21.com/movie/info/?movie_id=61056","retrieved":1706026966064,"image":"https://image.cine21.com/resize/cine21/poster/2023/1218/15_57_33__657fed5dd169b[X224,320].jpg"},{"title":"배우수업","contents":"개봉 : 2024-02-01","link":"http://www.cine21.com/movie/info/?movie_id=61174","retrieved":1706026966066,"image":"https://image.cine21.com/resize/cine21/poster/2024/0123/15_04_00__65af56d0e21b4[X224,320].jpg"},{"title":"데드맨","contents":"개봉 : 2024-02-07","link":"http://www.cine21.com/movie/info/?movie_id=58691","retrieved":1706026966075,"image":"https://image.cine21.com/resize/cine21/poster/2024/0109/18_13_54__659d0e52395ed[X224,320].jpg"},{"title":"영화 스미코구라시-푸른 달밤의 마법의 아이","contents":"개봉 : 2024-02-07","link":"http://www.cine21.com/movie/info/?movie_id=61173","retrieved":1706026966076,"image":"https://image.cine21.com/resize/cine21/poster/2024/0123/17_24_51__65af77d3b2ffe[X224,320].jpg"},{"title":"도그데이즈","contents":"개봉 : 2024-02-07","link":"http://www.cine21.com/movie/info/?movie_id=58779","retrieved":1706113334884,"image":"https://image.cine21.com/resize/cine21/poster/2024/0115/14_53_17__65a4c84de60e2[X224,320].jpg"},{"title":"플랜 75","contents":"개봉 : 2024-02-07","link":"http://www.cine21.com/movie/info/?movie_id=60231","retrieved":1706113334886,"image":"https://image.cine21.com/resize/cine21/poster/2024/0117/14_19_53__65a76379c720d[X224,320].jpg"},{"title":"아네모네","contents":"개봉 : 2024-02-07","link":"http://www.cine21.com/movie/info/?movie_id=61155","retrieved":1706026966073,"image":"https://image.cine21.com/resize/cine21/poster/2024/0123/11_06_00__65af1f083aef9[X224,320].jpg"},{"title":"아기상어 극장판: 사이렌 스톤의 비밀","contents":"개봉 : 2024-02-07","link":"http://www.cine21.com/movie/info/?movie_id=61130","retrieved":1706026966071,"image":"https://image.cine21.com/resize/cine21/poster/2024/0119/12_02_44__65a9e6546e56a[X224,320].jpg"},{"title":"검은 소년","contents":"개봉 : 2024-02-07","link":"http://www.cine21.com/movie/info/?movie_id=61125","retrieved":1706113334887,"image":"https://image.cine21.com/resize/cine21/poster/2024/0115/14_11_49__65a4be95285d8[X224,320].jpg"}]}