{"title":"씨네21 ─ 영화 ─ 개봉월 확정","url":"http://www.cine21.com/movie/lists/coming_month","favicon":"http://www.cine21.com/movie/lists/favicon.ico","elements":[{"title":"톡 투 미","contents":"개봉 : 2023-00","link":"http://www.cine21.com/movie/info/?movie_id=60872","retrieved":1695171176352,"image":"https://image.cine21.com/resize/cine21/poster/2023/0919/14_32_23__6509326745549[X224,320].jpg"},{"title":"나의 피투성이 연인","contents":"개봉 : 2023-00","link":"http://www.cine21.com/movie/info/?movie_id=60874","retrieved":1695171176349},{"title":"오르소","contents":"개봉 : 2023-09","link":"http://www.cine21.com/movie/info/?movie_id=60875","retrieved":1695171176352,"image":"https://image.cine21.com/resize/cine21/poster/2023/0919/16_05_38__65094842bd367[X224,320].jpg"},{"title":"책 종이 가위","contents":"개봉 : 2023-09","link":"http://www.cine21.com/movie/info/?movie_id=60804","retrieved":1695171176370,"image":"https://image.cine21.com/resize/cine21/poster/2023/0829/17_20_04__64edaa34576f6[X224,320].jpg"},{"title":"더 리프: 언더 워터","contents":"개봉 : 2023-09","link":"http://www.cine21.com/movie/info/?movie_id=60803","retrieved":1695171176381,"image":"https://image.cine21.com/resize/cine21/poster/2023/0828/15_54_15__64ec44972f0f1[X224,320].jpg"},{"title":"치악산","contents":"개봉 : 2023-09","link":"http://www.cine21.com/movie/info/?movie_id=60768","retrieved":1695171176359,"image":"https://image.cine21.com/resize/cine21/poster/2023/0912/17_13_34__65001dae0cc40[X224,320].jpg"},{"title":"다이브","contents":"개봉 : 2023-09","link":"http://www.cine21.com/movie/info/?movie_id=60767","retrieved":1695171176368},{"title":"킴스 비디오","contents":"개봉 : 2023-09","link":"http://www.cine21.com/movie/info/?movie_id=60812","retrieved":1695171176375,"image":"https://image.cine21.com/resize/cine21/poster/2023/0830/16_24_15__64eeee9f18d6d[X224,320].jpg"},{"title":"거미집","contents":"개봉 : 2023-09","link":"http://www.cine21.com/movie/info/?movie_id=60826","retrieved":1695171176385,"image":"https://image.cine21.com/resize/cine21/poster/2023/0912/14_38_08__64fff940560dd[X224,320].jpg"},{"title":"시카리오: 워 오브 건즈","contents":"개봉 : 2023-09","link":"http://www.cine21.com/movie/info/?movie_id=60892","retrieved":1695633321534,"image":"https://image.cine21.com/resize/cine21/poster/2023/0925/60892_65114b9280dff[X224,320].jpg"},{"title":"시수","contents":"개봉 : 2023-10","link":"http://www.cine21.com/movie/info/?movie_id=60888","retrieved":1695622771834,"image":"https://image.cine21.com/resize/cine21/poster/2023/0925/15_14_59__651125633dde7[X224,320].jpg"},{"title":"믿을 수 있는 사람","contents":"개봉 : 2023-10","link":"http://www.cine21.com/movie/info/?movie_id=60857","retrieved":1695171176403,"image":"https://image.cine21.com/resize/cine21/poster/2023/0926/14_25_13__65126b39626e6[X224,320].jpg"},{"title":"나의 행복한 결혼","contents":"개봉 : 2023-10","link":"http://www.cine21.com/movie/info/?movie_id=60856","retrieved":1695171176393,"image":"https://image.cine21.com/resize/cine21/poster/2023/0922/11_39_38__650cfe6ae5a43[X224,320].jpg"},{"title":"바람 따라 만나리 : 김호중의 계절","contents":"개봉 : 2023-10","link":"http://www.cine21.com/movie/info/?movie_id=60899","retrieved":1695784550713,"image":"https://image.cine21.com/resize/cine21/poster/2023/0926/17_17_02__6512937ed40af[X224,320].jpg"},{"title":"시뮬런트","contents":"개봉 : 2023-10","link":"http://www.cine21.com/movie/info/?movie_id=60818","retrieved":1695171176391,"image":"https://image.cine21.com/resize/cine21/poster/2023/0925/16_55_17__65113ce531731[X224,320].jpg"},{"title":"더 도터","contents":"개봉 : 2023-10","link":"http://www.cine21.com/movie/info/?movie_id=60898","retrieved":1695716340697,"image":"https://image.cine21.com/resize/cine21/poster/2023/0926/15_54_18__6512801a3fb7b[X224,320].jpg"},{"title":"너와 나","contents":"개봉 : 2023-10","link":"http://www.cine21.com/movie/info/?movie_id=60402","retrieved":1695784550718,"image":"https://image.cine21.com/resize/cine21/poster/2023/0828/17_44_51__64ec5e83a49e4[X224,320].jpg"},{"title":"레슬리에게","contents":"개봉 : 2023-10","link":"http://www.cine21.com/movie/info/?movie_id=60800","retrieved":1695784550726}]}