{"title":"씨네21 ─ 영화 ─ 개봉일 확정","url":"http://www.cine21.com/movie/lists/coming_date","favicon":"http://www.cine21.com/movie/lists/favicon.ico","elements":[{"title":"80일간의 세계일주","contents":"개봉 : 2023-09-00","link":"http://www.cine21.com/movie/info/?movie_id=60849","retrieved":1693894683268,"image":"https://image.cine21.com/resize/cine21/poster/2023/0905/15_59_00__64f6d1b4a4153[X224,320].jpg"},{"title":"돈 룩 디퍼","contents":"개봉 : 2023-09-07","link":"http://www.cine21.com/movie/info/?movie_id=60839","retrieved":1693322174113,"image":"https://image.cine21.com/resize/cine21/poster/2023/0829/13_31_49__64ed74b51faec[X224,320].jpg"},{"title":"앙드레 류: 러브 이즈 올 어라운드","contents":"개봉 : 2023-09-12","link":"http://www.cine21.com/movie/info/?movie_id=60840","retrieved":1693322174117,"image":"https://image.cine21.com/resize/cine21/poster/2023/0829/13_59_16__64ed7b241e496[X224,320].jpg"},{"title":"쿠렌치스 인 잘츠부르크","contents":"개봉 : 2023-09-13","link":"http://www.cine21.com/movie/info/?movie_id=60757","retrieved":1693322174131,"image":"https://image.cine21.com/resize/cine21/poster/2023/0731/16_26_20__64c7621cb18cd[X224,320].jpg"},{"title":"안녕, 내일 또 만나","contents":"개봉 : 2023-09-13","link":"http://www.cine21.com/movie/info/?movie_id=60785","retrieved":1693322174124,"image":"https://image.cine21.com/resize/cine21/poster/2023/0823/15_37_18__64e5a91e75793[X224,320].jpg"},{"title":"차박- 살인과 낭만의 밤","contents":"개봉 : 2023-09-13","link":"http://www.cine21.com/movie/info/?movie_id=60735","retrieved":1693322174128,"image":"https://image.cine21.com/resize/cine21/poster/2023/0829/13_06_54__64ed6edecf88d[X224,320].jpg"}]}