{"title":"씨네21 ─ 영화 ─ 현재 상영중","url":"http://www.cine21.com/movie/lists/playing","favicon":"http://www.cine21.com/movie/lists/favicon.ico","elements":[{"title":"생츄어리2: 쿼카가 너무해","contents":"개봉 : 2024-03-07","link":"http://www.cine21.com/movie/info/?movie_id=61085","retrieved":1709738491404,"image":"https://image.cine21.com/resize/cine21/poster/2024/0227/17_56_21__65dda3b501c07[X224,320].jpg"},{"title":"예수는 역사다","contents":"개봉 : 2024-03-07","link":"http://www.cine21.com/movie/info/?movie_id=50817","retrieved":1709738491417,"image":"https://image.cine21.com/resize/cine21/poster/2024/0305/14_59_07__65e6b4ab7cfea[X224,320].jpg"},{"title":"부활 그 소망","contents":"개봉 : 2024-03-07","link":"http://www.cine21.com/movie/info/?movie_id=61056","retrieved":1709738491401,"image":"https://image.cine21.com/resize/cine21/poster/2023/1218/15_57_33__657fed5dd169b[X224,320].jpg"},{"title":"파리 에펠탑 콘서트","contents":"개봉 : 2024-03-07","link":"http://www.cine21.com/movie/info/?movie_id=61323","retrieved":1709738491415,"image":"https://image.cine21.com/resize/cine21/poster/2024/0305/11_02_32__65e67d3848127[X224,320].jpg"},{"title":"비트","contents":"개봉 : 2024-03-06","link":"http://www.cine21.com/movie/info/?movie_id=4249","retrieved":1709651751043,"image":"https://image.cine21.com/resize/cine21/poster/2024/0219/17_07_06__65d30c2ad1279[X224,320].jpg"},{"title":"가여운 것들","contents":"개봉 : 2024-03-06","link":"http://www.cine21.com/movie/info/?movie_id=61096","retrieved":1709651751044,"image":"https://image.cine21.com/resize/cine21/poster/2024/0307/17_50_47__65e97fe70b0dc[X224,320].jpg"},{"title":"대결! 애니메이션","contents":"개봉 : 2024-03-06","link":"http://www.cine21.com/movie/info/?movie_id=60356","retrieved":1709651751045,"image":"https://image.cine21.com/resize/cine21/poster/2024/0214/10_55_10__65cc1d7e85fb2[X224,320].jpg"},{"title":"패스트 라이브즈","contents":"개봉 : 2024-03-06","link":"http://www.cine21.com/movie/info/?movie_id=61181","retrieved":1709651751041,"image":"https://image.cine21.com/resize/cine21/poster/2024/0307/11_55_33__65e92ca50629c[X224,320].jpg"},{"title":"벙커 게임","contents":"개봉 : 2024-03-06","link":"http://www.cine21.com/movie/info/?movie_id=61285","retrieved":1709651751041,"image":"https://image.cine21.com/resize/cine21/poster/2024/0216/12_10_20__65ced21c3e7e0[X224,320].jpg"},{"title":"스텝 업: 브레이킹","contents":"개봉 : 2024-03-06","link":"http://www.cine21.com/movie/info/?movie_id=61331","retrieved":1709709488986,"image":"https://image.cine21.com/resize/cine21/poster/2024/0306/17_21_10__65e82776c3bbf[X224,320].jpg"},{"title":"아이엠 티라노","contents":"개봉 : 2024-03-01","link":"http://www.cine21.com/movie/info/?movie_id=61235","retrieved":1709219836009},{"title":"듄: 파트2","contents":"개봉 : 2024-02-28","link":"http://www.cine21.com/movie/info/?movie_id=61093","retrieved":1709050898172,"image":"https://image.cine21.com/resize/cine21/poster/2024/0207/14_56_50__65c31ba2b289e[X224,320].jpg"},{"title":"여기는 아미코","contents":"개봉 : 2024-02-28","link":"http://www.cine21.com/movie/info/?movie_id=61236","retrieved":1709081667026,"image":"https://image.cine21.com/resize/cine21/poster/2024/0207/16_09_19__65c32c9fa42ef[X224,320].jpg"},{"title":"갓랜드","contents":"개봉 : 2024-02-28","link":"http://www.cine21.com/movie/info/?movie_id=61277","retrieved":1709050898175,"image":"https://image.cine21.com/resize/cine21/poster/2024/0221/11_10_35__65d55b9b4e623[X224,320].jpg"},{"title":"막걸리가 알려줄거야","contents":"개봉 : 2024-02-28","link":"http://www.cine21.com/movie/info/?movie_id=61150","retrieved":1709050898174,"image":"https://image.cine21.com/resize/cine21/poster/2024/0221/11_12_54__65d55c26638ae[X224,320].jpg"},{"title":"파묘","contents":"개봉 : 2024-02-22","link":"http://www.cine21.com/movie/info/?movie_id=61067","retrieved":1708528758113,"image":"https://image.cine21.com/resize/cine21/poster/2024/0223/18_55_45__65d86ba194e82[X224,320].jpg"},{"title":"유어 럭키 데이","contents":"개봉 : 2024-02-22","link":"http://www.cine21.com/movie/info/?movie_id=61279","retrieved":1708528758114,"image":"https://image.cine21.com/resize/cine21/poster/2024/0214/14_12_53__65cc4bd54e46c[X224,320].jpg"},{"title":"콜로니얼","contents":"개봉 : 2024-02-22","link":"http://www.cine21.com/movie/info/?movie_id=61286","retrieved":1708528758114,"image":"https://image.cine21.com/resize/cine21/poster/2024/0219/14_19_17__65d2e4d50dbdb[X224,320].jpg"}]}